pysmartcocoon/__init__.py
pysmartcocoon/__main__.py
pysmartcocoon/api.py
pysmartcocoon/const.py
pysmartcocoon/errors.py
pysmartcocoon/fan.py
pysmartcocoon/fan_helpers.py
pysmartcocoon/location.py
pysmartcocoon/manager.py
pysmartcocoon/room.py
pysmartcocoon/thermostat.py
pysmartcocoon/types.py
pysmartcocoon-1.4.2.dist-info/licenses/LICENSE.md
pysmartcocoon-1.4.2.dist-info/METADATA
pysmartcocoon-1.4.2.dist-info/WHEEL
pysmartcocoon-1.4.2.dist-info/top_level.txt
pysmartcocoon-1.4.2.dist-info/RECORD
