Metadata-Version: 2.4
Name: pysmartcocoon
Version: 1.4.2
Summary: Library built for Home Assistant to integrate with the SmartCocoon
Author-email: Dave Pearce <davepearce@live.com>
License-Expression: MIT
Project-URL: Homepage, https://github.com/davecpearce/pysmartcocoon
Keywords: smartcocoon,fan
Classifier: Programming Language :: Python
Classifier: Programming Language :: Python :: 3
Requires-Python: >=3.13.2
License-File: LICENSE.md
Requires-Dist: aiohttp>=3.8
Requires-Dist: async_timeout>=4.0
Provides-Extra: dev
Requires-Dist: black; extra == "dev"
Requires-Dist: build; extra == "dev"
Requires-Dist: bumpversion; extra == "dev"
Requires-Dist: pylint; extra == "dev"
Requires-Dist: twine; extra == "dev"
Provides-Extra: test
Requires-Dist: mypy; extra == "test"
Requires-Dist: pre-commit; extra == "test"
Requires-Dist: pytest; extra == "test"
Requires-Dist: pytest-cov; extra == "test"
Dynamic: license-file
